{
  "id": "01",
  "slug": "po-mans-dreams",
  "title": "Po' Man's Dreams",
  "bpm": 85,
  "key": "A min",
  "tags": [
    "dark",
    "angelic"
  ],
  "filterTags": [
    "in my feelings"
  ],
  "audioSrc": "po-mans-dreams.mp3",
  "root": 220,
  "peaks": [
    0.3,
    0.61,
    0.89,
    0.78,
    0.88,
    0.88,
    0.74,
    0.74,
    0.81,
    1.0,
    0.92,
    0.93,
    0.93,
    0.96,
    0.77,
    0.74,
    0.99,
    0.95,
    0.92,
    0.97,
    0.92,
    0.92,
    0.95,
    0.98,
    0.95,
    0.89,
    0.94,
    0.12
  ],
  "loudness": 1994.5,
  "lufs": -25.03
}
